setup.py
chords/__init__.py
chords/__version__.py
chords/_compat.py
chords/chord.py
chords/exceptions.py
chords/fairness_policies.py
chords/pool.py
chords/registry.py
chords/request.py
chords/resource.py
chords/task.py
chords.egg-info/PKG-INFO
chords.egg-info/SOURCES.txt
chords.egg-info/dependency_links.txt
chords.egg-info/requires.txt
chords.egg-info/top_level.txt
chords/more/__init__.py
chords/more/gevent_task.py
tests/more/__init__.py
tests/more/test_gevent.py