Metadata-Version: 1.1
Name: chords
Version: 0.5.0
Summary: Simple task and resource management
Home-page: http://omergertel.github.io/chords
Author: Omer Gertel
Author-email: omer.gertel@gmail.com
License: MIT
Platform: UNKNOWN
Classifier: Programming Language :: Python :: 2.7
Classifier: Programming Language :: Python :: 3.4
